django_inspect_tasks/__init__.py
django_inspect_tasks/management/__init__.py
django_inspect_tasks/management/commands/__init__.py
django_inspect_tasks/management/commands/tasks.py
django_inspect_tasks/util.py
django_inspect_tasks-0.6.0.dist-info/WHEEL
django_inspect_tasks-0.6.0.dist-info/METADATA
django_inspect_tasks-0.6.0.dist-info/RECORD
