Metadata-Version: 2.4
Name: django-inspect-tasks
Version: 0.6.0
Summary: Inspect Tasks in your Django App
Keywords: django,tasks
Author: Paul Traylor
Author-email: Paul Traylor <kungfudiscomonkey@gmail.com>
License-Expression: MIT
Classifier: Development Status :: 3 - Alpha
Classifier: Framework :: Django :: 6.0
Classifier: Programming Language :: Python :: 3.12
Classifier: Programming Language :: Python :: 3.13
Classifier: Programming Language :: Python :: 3.14
Classifier: Programming Language :: Python :: 3.15
Requires-Dist: django-crontask>=1.0.3
Requires-Dist: django>=6.0
Requires-Python: >=3.12
Project-URL: download, https://pypi.org/project/django-inspect-tasks/
Project-URL: issues, https://codeberg.org/kfdm/django-inspect-tasks/issues
Project-URL: source, https://codeberg.org/kfdm/django-inspect-tasks
